rustac/__init__.py
rustac/geoparquet.py
rustac/py.typed
rustac/rustac.abi3.so
rustac/rustac.pyi
rustac-0.9.3.dist-info/METADATA
rustac-0.9.3.dist-info/WHEEL
rustac-0.9.3.dist-info/entry_points.txt
rustac-0.9.3.dist-info/licenses/LICENSE-APACHE
rustac-0.9.3.dist-info/licenses/LICENSE-MIT
rustac-0.9.3.dist-info/RECORD
