Metadata-Version: 2.4
Name: rustac
Version: 0.9.3
Classifier: Development Status :: 4 - Beta
Classifier: Intended Audience :: Science/Research
Classifier: License :: OSI Approved :: Apache Software License
Classifier: License :: OSI Approved :: MIT License
Classifier: Natural Language :: English
Classifier: Programming Language :: Python :: 3.11
Classifier: Programming Language :: Python :: 3.12
Classifier: Programming Language :: Python :: 3.13
Classifier: Programming Language :: Python :: 3.14
Classifier: Programming Language :: Python :: Implementation :: CPython
Classifier: Programming Language :: Rust
Classifier: Typing :: Typed
Requires-Dist: arro3-core>=0.4.5 ; extra == 'arrow'
Provides-Extra: arrow
License-File: LICENSE-APACHE
License-File: LICENSE-MIT
Summary: The power of Rust for the Python STAC ecosystem
Keywords: stac,geospatial
Author-email: Pete Gadomski <pete.gadomski@gmail.com>
Requires-Python: >=3.11
Project-URL: Documentation, https://stac-utils.github.io/rustac-py
Project-URL: Issues, https://github.com/stac-utils/rustac-py/issues
Project-URL: Repository, https://github.com/stac-utils/rustac-py
